aerialer/BashCLI.py
aerialer/Commander.py
aerialer/Generator.py
aerialer/Transmitter.py
aerialer/__init__.py
aerialer/cluster/Qsub.py
aerialer/cluster/Slurm.py
aerialer/cluster/__init__.py
aerialer/data/1a11.job
aerialer/data/1a91.job
aerialer/job.py
aerialer-0.1.2.dist-info/LICENSE
aerialer-0.1.2.dist-info/METADATA
aerialer-0.1.2.dist-info/WHEEL
aerialer-0.1.2.dist-info/RECORD
