Metadata-Version: 2.3
Name: aerialer
Version: 0.1.2
Summary: 
Author: Jianfeng Sun
Author-email: jianfeng.sunmt@gmail.com
Requires-Python: >=3.11
Classifier: Programming Language :: Python :: 3
Classifier: Programming Language :: Python :: 3.11
Classifier: Programming Language :: Python :: 3.12
Classifier: Programming Language :: Python :: 3.13
Requires-Dist: click (>=8.2.1,<9.0.0)
